.gitignore
AUTHORS
LICENSE
README.md
setup.py
wallaby/__init__.py
wallaby.egg-info/PKG-INFO
wallaby.egg-info/SOURCES.txt
wallaby.egg-info/dependency_links.txt
wallaby.egg-info/requires.txt
wallaby.egg-info/top_level.txt