Metadata-Version: 1.1
Name: wallaby
Version: 0.1.2
Summary: Wallaby is a powerful yet simple framework for building Qt-based, cross-platform applications in PyQt/PySide with a CouchDB/CouchBase and Elasticsearch backend.
Home-page: https://github.com/FreshXOpenSource
Author: FreshX GbR
Author-email: wallaby@freshx.de
License: BSD
Platform: UNKNOWN
Classifier: Development Status :: 4 - Beta
Classifier: Environment :: MacOS X
Classifier: Environment :: Win32 (MS Windows)
Classifier: Environment :: X11 Applications
Classifier: Framework :: Twisted
Classifier: Intended Audience :: Developers
Classifier: Intended Audience :: System Administrators
Classifier: License :: OSI Approved :: BSD License
Classifier: Operating System :: MacOS :: MacOS X
Classifier: Operating System :: Microsoft :: Windows
Classifier: Operating System :: POSIX :: Linux
Classifier: Programming Language :: Python :: 2.7
Classifier: Topic :: Software Development :: Libraries :: Application Frameworks
